LICENSE
atlaspyapi/__init__.py
atlaspyapi/base.py
atlaspyapi/client.py
atlaspyapi/config/config.ini
atlaspyapi/definition.py
atlaspyapi/docs/EntityManagerApiHelper.py
atlaspyapi/docs/__init__.py
atlaspyapi/entity_management/EntityManager.py
atlaspyapi/entity_management/__init__.py
atlaspyapi/entity_management/hive/HiveColumnManager.py
atlaspyapi/entity_management/hive/HiveDBManager.py
atlaspyapi/entity_management/hive/HiveTableManager.py
atlaspyapi/entity_management/hive/__init__.py
atlaspyapi/entity_management/s3/S3BucketManager.py
atlaspyapi/entity_management/s3/S3ObjectManager.py
atlaspyapi/entity_management/s3/S3PsDirManager.py
atlaspyapi/entity_management/s3/__init__.py
atlaspyapi/entity_search/EntityFinder.py
atlaspyapi/entity_search/__init__.py
atlaspyapi/entity_source_generation/HiveColumnEntityGenerator.py
atlaspyapi/entity_source_generation/HiveDBEntityGenerator.py
atlaspyapi/entity_source_generation/HiveTableEntityGenerator.py
atlaspyapi/entity_source_generation/S3BucketEntityGenerator.py
atlaspyapi/entity_source_generation/S3ObjectEntityGenerator.py
atlaspyapi/entity_source_generation/S3PsDirEntityGenerator.py
atlaspyapi/entity_source_generation/__init__.py
atlaspyapi/entity_source_generation/template/aws_s3_bucket.json.j2
atlaspyapi/entity_source_generation/template/aws_s3_object.json.j2
atlaspyapi/entity_source_generation/template/aws_s3_pseudo_dir.json.j2
atlaspyapi/entity_source_generation/template/hive_column.json.j2
atlaspyapi/entity_source_generation/template/hive_db.json.j2
atlaspyapi/entity_source_generation/template/hive_table.json.j2
atlaspyapi/entity_source_generation/utile.py
atlaspyapi/events.py
atlaspyapi/exceptions.py
atlaspyapi/log_manager.py
atlaspyapi/models.py
atlaspyapi/utils.py
atlaspyapi-0.2.8.dist-info/LICENSE
atlaspyapi-0.2.8.dist-info/WHEEL
atlaspyapi-0.2.8.dist-info/METADATA
atlaspyapi-0.2.8.dist-info/RECORD
