Metadata-Version: 2.1
Name: atlaspyapi
Version: 0.2.8
Summary: 
Home-page: https://github.com/pengfei99/AtlasPyApi
License: Apache-2.0
Keywords: keyword,another_keyword
Author: pengfei
Author-email: liu.pengfei@hotmail.fr
Requires-Python: >=3.8,<4.0
Classifier: License :: OSI Approved :: Apache Software License
Classifier: Programming Language :: Python :: 3
Classifier: Programming Language :: Python :: 3.8
Classifier: Programming Language :: Python :: 3.9
Classifier: Programming Language :: Python :: 3.10
Classifier: Programming Language :: Python :: 3.11
Requires-Dist: Jinja2 (>=3.0.3,<4.0.0)
Requires-Dist: click (>=8.1.2,<9.0.0)
Requires-Dist: requests (>=2.27.1,<3.0.0)
Requires-Dist: six (>=1.16.0,<2.0.0)
Project-URL: Repository, https://github.com/pengfei99/AtlasPyApi
